decorator_composer/__init__.py
decorator_composer-0.0.1.dist-info/METADATA
decorator_composer-0.0.1.dist-info/WHEEL
decorator_composer-0.0.1.dist-info/top_level.txt
decorator_composer-0.0.1.dist-info/RECORD
