Metadata-Version: 2.1
Name: decorator_composer
Version: 0.0.1
Summary: simple utility to compose decorators
